pypbt/__init__.py
pypbt/domains.py
pypbt/quantifiers.py
pypbt/runner/__init__.py
pypbt/runner/runners.py
pypbt/state_machine.py
pypbt-0.2.1.dist-info/entry_points.txt
pypbt-0.2.1.dist-info/LICENSE
pypbt-0.2.1.dist-info/WHEEL
pypbt-0.2.1.dist-info/METADATA
pypbt-0.2.1.dist-info/RECORD
