Metadata-Version: 2.1
Name: pypbt
Version: 0.2.1
Summary: Library of functions to write Property Based Tests in python
Home-page: https://github.com/cabrero/pypbt
License: GPL-2.0-only
Author: David Cabrero Souto
Author-email: david.cabrero@madsgroup.org
Requires-Python: >=3.10,<4.0
Classifier: Development Status :: 4 - Beta
Classifier: Environment :: Console
Classifier: Intended Audience :: Developers
Classifier: License :: OSI Approved :: GNU General Public License v2 (GPLv2)
Classifier: Programming Language :: Python :: 3
Classifier: Programming Language :: Python :: 3.10
Classifier: Programming Language :: Python :: 3
Classifier: Topic :: Software Development :: Libraries :: Python Modules
Classifier: Topic :: Software Development :: Quality Assurance
Classifier: Topic :: Software Development :: Testing
Requires-Dist: rich (>=12.4.4,<13.0.0)
Project-URL: Bug Tracker, https://github.com/cabrero/pypbt/issues
Project-URL: Documentation, https://pypbt.readthedocs.io/en/latest/
